setup.py
gusbi_distributions/Binomialdistribution.py
gusbi_distributions/Gaussiandistribution.py
gusbi_distributions/Generaldistribution.py
gusbi_distributions/__init__.py
gusbi_distributions.egg-info/PKG-INFO
gusbi_distributions.egg-info/SOURCES.txt
gusbi_distributions.egg-info/dependency_links.txt
gusbi_distributions.egg-info/not-zip-safe
gusbi_distributions.egg-info/top_level.txt