Metadata-Version: 1.0
Name: gusbi-distributions
Version: 0.1
Summary: Gaussian and Binomial distributions
Home-page: UNKNOWN
Author: Lawrence Agyepong
Author-email: agyeponglawrence101@gmail.com
License: UNKNOWN
Platform: UNKNOWN
